qt_wsi_reg/__init__.py
qt_wsi_reg/registration_tree.py
qt_wsi_registration-0.0.14.dist-info/licenses/LICENSE
tests/__init__.py
tests/test_ccmct.py
tests/test_cyto.py
tests/test_ihche.py
tests/test_rotation.py
qt_wsi_registration-0.0.14.dist-info/METADATA
qt_wsi_registration-0.0.14.dist-info/WHEEL
qt_wsi_registration-0.0.14.dist-info/top_level.txt
qt_wsi_registration-0.0.14.dist-info/RECORD
