Metadata-Version: 2.4
Name: qt-wsi-registration
Version: 0.0.14
Summary: Robust quad-tree based registration on whole slide images
Home-page: https://github.com/ChristianMarzahl/WsiRegistration
Author: Christian Marzahl
Author-email: christian.marzahl@gamil.com
Classifier: Programming Language :: Python :: 3
Classifier: License :: OSI Approved :: MIT License
Classifier: Operating System :: OS Independent
Requires-Python: >=3.6
License-File: LICENSE
Requires-Dist: numpy
Requires-Dist: opencv-python
Requires-Dist: openslide-python
Requires-Dist: matplotlib
Requires-Dist: scikit-learn
Requires-Dist: probreg==0.3.5
Requires-Dist: pillow
Requires-Dist: scipy
Dynamic: author
Dynamic: author-email
Dynamic: classifier
Dynamic: description
Dynamic: description-content-type
Dynamic: home-page
Dynamic: license-file
Dynamic: requires-dist
Dynamic: requires-python
Dynamic: summary
